<?xml version="1.0" encoding="utf-8"?>
<SoundBanksInfo Platform="Mac" BasePlatform="Mac" SchemaVersion="12" SoundbankVersion="140">
	<RootPaths>
		<ProjectRoot>D:\Masters Sem 2\EAE 6110 Game Projects\BattleBard\BattleBard\BattleBard\BattleBard_WwiseProject\</ProjectRoot>
		<SourceFilesRoot>D:\Masters Sem 2\EAE 6110 Game Projects\BattleBard\BattleBard\BattleBard\BattleBard_WwiseProject\.cache\Mac\</SourceFilesRoot>
		<SoundBanksRoot>D:\Masters Sem 2\EAE 6110 Game Projects\BattleBard\BattleBard\BattleBard\BattleBard_WwiseProject\GeneratedSoundBanks\Mac\</SoundBanksRoot>
		<ExternalSourcesInputFile></ExternalSourcesInputFile>
		<ExternalSourcesOutputRoot>D:\Masters Sem 2\EAE 6110 Game Projects\BattleBard\BattleBard\BattleBard\BattleBard_WwiseProject\GeneratedSoundBanks\Mac</ExternalSourcesOutputRoot>
	</RootPaths>
	<DialogueEvents/>
	<StreamedFiles/>
	<MediaFilesNotInAnyBank/>
	<SoundBanks>
		<SoundBank Id="393239870" Language="SFX" Hash="2781064673">
			<ObjectPath>\SoundBanks\Default Work Unit\SFX</ObjectPath>
			<ShortName>SFX</ShortName>
			<Path>SFX.bnk</Path>
			<IncludedEvents>
				<Event Id="2692890187" Name="Play_A_Troll" ObjectPath="\Events\Default Work Unit\Play_A_Troll" DurationType="OneShot" DurationMin="2.498292" DurationMax="2.498292"/>
				<Event Id="1318683030" Name="Play_Drum_1" ObjectPath="\Events\Default Work Unit\Play_Drum_1" DurationType="OneShot" DurationMin="2." DurationMax="2."/>
				<Event Id="1318683029" Name="Play_Drum_2" ObjectPath="\Events\Default Work Unit\Play_Drum_2" DurationType="OneShot" DurationMin="2." DurationMax="2."/>
				<Event Id="1318683028" Name="Play_Drum_3" ObjectPath="\Events\Default Work Unit\Play_Drum_3" DurationType="OneShot" DurationMin="2." DurationMax="2."/>
				<Event Id="1318683027" Name="Play_Drum_4" ObjectPath="\Events\Default Work Unit\Play_Drum_4" DurationType="OneShot" DurationMin="2." DurationMax="2."/>
				<Event Id="3103472528" Name="Play_Intro" ObjectPath="\Events\Default Work Unit\Play_Intro" DurationType="OneShot" DurationMin="31.086916" DurationMax="31.086916"/>
				<Event Id="3670347913" Name="Play_Metronome_ms" ObjectPath="\Events\Default Work Unit\Play_Metronome_ms" DurationType="OneShot" DurationMin="0.050045" DurationMax="0.050045"/>
				<Event Id="3895177024" Name="Play_Metronome_s" ObjectPath="\Events\Default Work Unit\Play_Metronome_s" DurationType="Infinite"/>
				<Event Id="226855043" Name="Play_Reinforced_Gate" ObjectPath="\Events\Default Work Unit\Play_Reinforced_Gate" DurationType="OneShot" DurationMin="5.557167" DurationMax="5.557167"/>
				<Event Id="1807275314" Name="Play_Take_Back_Our_Home" ObjectPath="\Events\Default Work Unit\Play_Take_Back_Our_Home" DurationType="OneShot" DurationMin="3.017333" DurationMax="3.017333"/>
				<Event Id="3448951123" Name="Play_That_One_There" ObjectPath="\Events\Default Work Unit\Play_That_One_There" DurationType="OneShot" DurationMin="6.789021" DurationMax="6.789021"/>
				<Event Id="1170258016" Name="Play_The_Village_is_Ours_Again" ObjectPath="\Events\Default Work Unit\Play_The_Village_is_Ours_Again" DurationType="OneShot" DurationMin="9.197354" DurationMax="9.197354"/>
				<Event Id="2831686769" Name="Play_Theyre_Retreating" ObjectPath="\Events\Default Work Unit\Play_Theyre_Retreating" DurationType="OneShot" DurationMin="7.162708" DurationMax="7.162708"/>
				<Event Id="3559424791" Name="Play_Trap" ObjectPath="\Events\Default Work Unit\Play_Trap" DurationType="OneShot" DurationMin="7.55025" DurationMax="7.55025"/>
				<Event Id="1123782303" Name="Play_We_Need_More_Muscle" ObjectPath="\Events\Default Work Unit\Play_We_Need_More_Muscle" DurationType="OneShot" DurationMin="2.802813" DurationMax="2.802813"/>
			</IncludedEvents>
			<IncludedMemoryFiles>
				<File Id="67889240" Language="SFX">
					<ShortName>Theyre_Retreating_3.wav</ShortName>
					<Path>SFX\Theyre_Retreating_3_10C4C929.wem</Path>
				</File>
				<File Id="190032006" Language="SFX">
					<ShortName>A_Troll_1.wav</ShortName>
					<Path>SFX\A_Troll_1_10C4C929.wem</Path>
				</File>
				<File Id="294660824" Language="SFX">
					<ShortName>Intro_2.wav</ShortName>
					<Path>SFX\Intro_2_10C4C929.wem</Path>
				</File>
				<File Id="322211726" Language="SFX">
					<ShortName>Drum 2.wav</ShortName>
					<Path>SFX\Drum 2_10C4C929.wem</Path>
				</File>
				<File Id="351928753" Language="SFX">
					<ShortName>The_Village_is_Ours_Again_1.wav</ShortName>
					<Path>SFX\The_Village_is_Ours_Again_1_10C4C929.wem</Path>
				</File>
				<File Id="390141292" Language="SFX">
					<ShortName>Drum 4.wav</ShortName>
					<Path>SFX\Drum 4_10C4C929.wem</Path>
				</File>
				<File Id="468849986" Language="SFX">
					<ShortName>That_One_There_2.wav</ShortName>
					<Path>SFX\That_One_There_2_10C4C929.wem</Path>
				</File>
				<File Id="556155814" Language="SFX">
					<ShortName>Take_Back_Our_Home_2.wav</ShortName>
					<Path>SFX\Take_Back_Our_Home_2_10C4C929.wem</Path>
				</File>
				<File Id="608074595" Language="SFX">
					<ShortName>We_Need_More_Muscle_3.wav</ShortName>
					<Path>SFX\We_Need_More_Muscle_3_10C4C929.wem</Path>
				</File>
				<File Id="631214722" Language="SFX">
					<ShortName>Metronome.wav</ShortName>
					<Path>SFX\Metronome_10C4C929.wem</Path>
				</File>
				<File Id="660299775" Language="SFX">
					<ShortName>Metronome_New.wav</ShortName>
					<Path>SFX\Metronome_New_D79FB2B7.wem</Path>
				</File>
				<File Id="758886743" Language="SFX">
					<ShortName>Drum 1.wav</ShortName>
					<Path>SFX\Drum 1_10C4C929.wem</Path>
				</File>
				<File Id="988406303" Language="SFX">
					<ShortName>Reinforced_Gate_1.wav</ShortName>
					<Path>SFX\Reinforced_Gate_1_10C4C929.wem</Path>
				</File>
				<File Id="1000564919" Language="SFX">
					<ShortName>Drum 3.wav</ShortName>
					<Path>SFX\Drum 3_10C4C929.wem</Path>
				</File>
				<File Id="1045215813" Language="SFX">
					<ShortName>Trap_1.wav</ShortName>
					<Path>SFX\Trap_1_10C4C929.wem</Path>
				</File>
			</IncludedMemoryFiles>
			<GameParameters>
				<GameParameter Id="988953028" Name="SFXVolume" ObjectPath="\Game Parameters\Default Work Unit\Volume\SFXVolume"/>
				<GameParameter Id="2346531308" Name="MusicVolume" ObjectPath="\Game Parameters\Default Work Unit\Volume\MusicVolume"/>
				<GameParameter Id="2591469393" Name="MetronomeVolume" ObjectPath="\Game Parameters\Default Work Unit\Volume\MetronomeVolume"/>
				<GameParameter Id="2918011349" Name="MasterVolume" ObjectPath="\Game Parameters\Default Work Unit\Volume\MasterVolume"/>
				<GameParameter Id="3325181466" Name="VOVolume" ObjectPath="\Game Parameters\Default Work Unit\Volume\VOVolume"/>
			</GameParameters>
		</SoundBank>
		<SoundBank Id="1355168291" Language="SFX" Hash="3291146305">
			<ObjectPath>Init</ObjectPath>
			<ShortName>Init</ShortName>
			<Path>Init.bnk</Path>
			<GameParameters>
				<GameParameter Id="988953028" Name="SFXVolume" ObjectPath="\Game Parameters\Default Work Unit\Volume\SFXVolume"/>
				<GameParameter Id="2346531308" Name="MusicVolume" ObjectPath="\Game Parameters\Default Work Unit\Volume\MusicVolume"/>
				<GameParameter Id="2591469393" Name="MetronomeVolume" ObjectPath="\Game Parameters\Default Work Unit\Volume\MetronomeVolume"/>
				<GameParameter Id="2918011349" Name="MasterVolume" ObjectPath="\Game Parameters\Default Work Unit\Volume\MasterVolume"/>
				<GameParameter Id="3325181466" Name="VOVolume" ObjectPath="\Game Parameters\Default Work Unit\Volume\VOVolume"/>
			</GameParameters>
		</SoundBank>
		<SoundBank Id="2386706874" Language="SFX" Hash="2213890130">
			<ObjectPath>\SoundBanks\Default Work Unit\Music_120_bpm</ObjectPath>
			<ShortName>Music_120_bpm</ShortName>
			<Path>Music_120_bpm.bnk</Path>
			<IncludedEvents>
				<Event Id="2692890187" Name="Play_A_Troll" ObjectPath="\Events\Default Work Unit\Play_A_Troll" DurationType="OneShot" DurationMin="2.498292" DurationMax="2.498292">
					<IncludedMemoryFiles>
						<File Id="190032006" Language="SFX">
							<ShortName>A_Troll_1.wav</ShortName>
							<Path>SFX\A_Troll_1_10C4C929.wem</Path>
						</File>
					</IncludedMemoryFiles>
				</Event>
				<Event Id="3113730691" Name="Play_bg_music" ObjectPath="\Events\Default Work Unit\Play_bg_music" DurationType="Infinite">
					<IncludedMemoryFiles>
						<File Id="904612785" Language="SFX">
							<ShortName>bg_music.wav</ShortName>
							<Path>SFX\bg_music_D79FB2B7.wem</Path>
						</File>
					</IncludedMemoryFiles>
				</Event>
				<Event Id="2037311474" Name="Play_Combo_Tiers" ObjectPath="\Events\Default Work Unit\Play_Combo_Tiers" DurationType="Infinite">
					<IncludedMemoryFiles>
						<File Id="90544307" Language="SFX">
							<ShortName>Attack_T2_3.wav</ShortName>
							<Path>SFX\Attack_T2_3_D79FB2B7.wem</Path>
						</File>
						<File Id="106126622" Language="SFX">
							<ShortName>Healing_T2_1.wav</ShortName>
							<Path>SFX\Healing_T2_1_D79FB2B7.wem</Path>
						</File>
						<File Id="141807743" Language="SFX">
							<ShortName>Healing_T2_2.wav</ShortName>
							<Path>SFX\Healing_T2_2_D79FB2B7.wem</Path>
						</File>
						<File Id="153062155" Language="SFX">
							<ShortName>Attack_T2_1.wav</ShortName>
							<Path>SFX\Attack_T2_1_D79FB2B7.wem</Path>
						</File>
						<File Id="163595620" Language="SFX">
							<ShortName>Speed_T1_1.wav</ShortName>
							<Path>SFX\Speed_T1_1_D79FB2B7.wem</Path>
						</File>
						<File Id="185803366" Language="SFX">
							<ShortName>Healing_T1_1.wav</ShortName>
							<Path>SFX\Healing_T1_1_D79FB2B7.wem</Path>
						</File>
						<File Id="211984583" Language="SFX">
							<ShortName>Attack_T3_2.wav</ShortName>
							<Path>SFX\Attack_T3_2_D79FB2B7.wem</Path>
						</File>
						<File Id="216635119" Language="SFX">
							<ShortName>Attack_T2_2.wav</ShortName>
							<Path>SFX\Attack_T2_2_D79FB2B7.wem</Path>
						</File>
						<File Id="242612734" Language="SFX">
							<ShortName>Speed_T2_2.wav</ShortName>
							<Path>SFX\Speed_T2_2_D79FB2B7.wem</Path>
						</File>
						<File Id="272182380" Language="SFX">
							<ShortName>Speed_T1_2.wav</ShortName>
							<Path>SFX\Speed_T1_2_D79FB2B7.wem</Path>
						</File>
						<File Id="307168888" Language="SFX">
							<ShortName>Healing_T2_3.wav</ShortName>
							<Path>SFX\Healing_T2_3_D79FB2B7.wem</Path>
						</File>
						<File Id="336345604" Language="SFX">
							<ShortName>Healing_T3_3.wav</ShortName>
							<Path>SFX\Healing_T3_3_D79FB2B7.wem</Path>
						</File>
						<File Id="351337165" Language="SFX">
							<ShortName>Healing_T3_1.wav</ShortName>
							<Path>SFX\Healing_T3_1_D79FB2B7.wem</Path>
						</File>
						<File Id="408029112" Language="SFX">
							<ShortName>Healing_T3_2.wav</ShortName>
							<Path>SFX\Healing_T3_2_D79FB2B7.wem</Path>
						</File>
						<File Id="459815666" Language="SFX">
							<ShortName>Speed_T1_3.wav</ShortName>
							<Path>SFX\Speed_T1_3_D79FB2B7.wem</Path>
						</File>
						<File Id="475942752" Language="SFX">
							<ShortName>Speed_T3_1.wav</ShortName>
							<Path>SFX\Speed_T3_1_D79FB2B7.wem</Path>
						</File>
						<File Id="587467227" Language="SFX">
							<ShortName>Attack_T1_1.wav</ShortName>
							<Path>SFX\Attack_T1_1_D79FB2B7.wem</Path>
						</File>
						<File Id="620322888" Language="SFX">
							<ShortName>Speed_T2_3.wav</ShortName>
							<Path>SFX\Speed_T2_3_D79FB2B7.wem</Path>
						</File>
						<File Id="654632406" Language="SFX">
							<ShortName>Attack_T1_3.wav</ShortName>
							<Path>SFX\Attack_T1_3_D79FB2B7.wem</Path>
						</File>
						<File Id="710055089" Language="SFX">
							<ShortName>Speed_T2_1.wav</ShortName>
							<Path>SFX\Speed_T2_1_D79FB2B7.wem</Path>
						</File>
						<File Id="729255060" Language="SFX">
							<ShortName>Speed_T3_3.wav</ShortName>
							<Path>SFX\Speed_T3_3_D79FB2B7.wem</Path>
						</File>
						<File Id="731989350" Language="SFX">
							<ShortName>Healing_T1_3.wav</ShortName>
							<Path>SFX\Healing_T1_3_D79FB2B7.wem</Path>
						</File>
						<File Id="784377917" Language="SFX">
							<ShortName>Attack_T3_3.wav</ShortName>
							<Path>SFX\Attack_T3_3_D79FB2B7.wem</Path>
						</File>
						<File Id="931607762" Language="SFX">
							<ShortName>Attack_T1_2.wav</ShortName>
							<Path>SFX\Attack_T1_2_D79FB2B7.wem</Path>
						</File>
						<File Id="1020229655" Language="SFX">
							<ShortName>Speed_T3_2.wav</ShortName>
							<Path>SFX\Speed_T3_2_D79FB2B7.wem</Path>
						</File>
						<File Id="1028794606" Language="SFX">
							<ShortName>Attack_T3_1.wav</ShortName>
							<Path>SFX\Attack_T3_1_D79FB2B7.wem</Path>
						</File>
						<File Id="1063858419" Language="SFX">
							<ShortName>Healing_T1_2.wav</ShortName>
							<Path>SFX\Healing_T1_2_D79FB2B7.wem</Path>
						</File>
					</IncludedMemoryFiles>
					<SwitchContainers>
						<SwitchContainer SwitchValue="{CD64C491-2F3A-4CA5-B7A8-EAD578BDE4DD}">
							<Media>
								<File Id="185803366"/>
								<File Id="731989350"/>
								<File Id="1063858419"/>
							</Media>
						</SwitchContainer>
						<SwitchContainer SwitchValue="{5D8C8D93-8CE3-48DC-8CF1-2555AC325FAB}">
							<Media>
								<File Id="211984583"/>
								<File Id="784377917"/>
								<File Id="1028794606"/>
							</Media>
						</SwitchContainer>
						<SwitchContainer SwitchValue="{063107F4-D107-4DEE-9841-86FC95AF9026}">
							<Media>
								<File Id="475942752"/>
								<File Id="729255060"/>
								<File Id="1020229655"/>
							</Media>
						</SwitchContainer>
						<SwitchContainer SwitchValue="{343A886D-F1FF-4890-8F4A-005D4F62AB06}">
							<Media>
								<File Id="163595620"/>
								<File Id="272182380"/>
								<File Id="459815666"/>
							</Media>
						</SwitchContainer>
						<SwitchContainer SwitchValue="{5F20EC0D-AAA5-4CF4-91E7-9B4E4F92B40F}">
							<Media>
								<File Id="587467227"/>
								<File Id="654632406"/>
								<File Id="931607762"/>
							</Media>
						</SwitchContainer>
						<SwitchContainer SwitchValue="{14B566F9-61CE-480B-B4E2-16A2DA945C22}">
							<Media>
								<File Id="242612734"/>
								<File Id="620322888"/>
								<File Id="710055089"/>
							</Media>
						</SwitchContainer>
						<SwitchContainer SwitchValue="{DC578820-B7C8-4441-914C-34F9C419D1B3}">
							<Media>
								<File Id="106126622"/>
								<File Id="141807743"/>
								<File Id="307168888"/>
							</Media>
						</SwitchContainer>
						<SwitchContainer SwitchValue="{227E5162-1662-4732-88B2-F93AF2AE298A}">
							<Media>
								<File Id="336345604"/>
								<File Id="351337165"/>
								<File Id="408029112"/>
							</Media>
						</SwitchContainer>
						<SwitchContainer SwitchValue="{4C56F35B-E8B1-4EBE-92DC-68A45E93C1A8}">
							<Media>
								<File Id="90544307"/>
								<File Id="153062155"/>
								<File Id="216635119"/>
							</Media>
						</SwitchContainer>
					</SwitchContainers>
				</Event>
				<Event Id="1318683030" Name="Play_Drum_1" ObjectPath="\Events\Default Work Unit\Play_Drum_1" DurationType="OneShot" DurationMin="2." DurationMax="2.">
					<IncludedMemoryFiles>
						<File Id="758886743" Language="SFX">
							<ShortName>Drum 1.wav</ShortName>
							<Path>SFX\Drum 1_10C4C929.wem</Path>
						</File>
					</IncludedMemoryFiles>
				</Event>
				<Event Id="1318683029" Name="Play_Drum_2" ObjectPath="\Events\Default Work Unit\Play_Drum_2" DurationType="OneShot" DurationMin="2." DurationMax="2.">
					<IncludedMemoryFiles>
						<File Id="322211726" Language="SFX">
							<ShortName>Drum 2.wav</ShortName>
							<Path>SFX\Drum 2_10C4C929.wem</Path>
						</File>
					</IncludedMemoryFiles>
				</Event>
				<Event Id="1318683028" Name="Play_Drum_3" ObjectPath="\Events\Default Work Unit\Play_Drum_3" DurationType="OneShot" DurationMin="2." DurationMax="2.">
					<IncludedMemoryFiles>
						<File Id="1000564919" Language="SFX">
							<ShortName>Drum 3.wav</ShortName>
							<Path>SFX\Drum 3_10C4C929.wem</Path>
						</File>
					</IncludedMemoryFiles>
				</Event>
				<Event Id="1318683027" Name="Play_Drum_4" ObjectPath="\Events\Default Work Unit\Play_Drum_4" DurationType="OneShot" DurationMin="2." DurationMax="2.">
					<IncludedMemoryFiles>
						<File Id="390141292" Language="SFX">
							<ShortName>Drum 4.wav</ShortName>
							<Path>SFX\Drum 4_10C4C929.wem</Path>
						</File>
					</IncludedMemoryFiles>
				</Event>
				<Event Id="3103472528" Name="Play_Intro" ObjectPath="\Events\Default Work Unit\Play_Intro" DurationType="OneShot" DurationMin="31.086916" DurationMax="31.086916">
					<IncludedMemoryFiles>
						<File Id="294660824" Language="SFX">
							<ShortName>Intro_2.wav</ShortName>
							<Path>SFX\Intro_2_10C4C929.wem</Path>
						</File>
					</IncludedMemoryFiles>
				</Event>
				<Event Id="3670347913" Name="Play_Metronome_ms" ObjectPath="\Events\Default Work Unit\Play_Metronome_ms" DurationType="OneShot" DurationMin="0.050045" DurationMax="0.050045">
					<IncludedMemoryFiles>
						<File Id="631214722" Language="SFX">
							<ShortName>Metronome.wav</ShortName>
							<Path>SFX\Metronome_10C4C929.wem</Path>
						</File>
					</IncludedMemoryFiles>
				</Event>
				<Event Id="3895177024" Name="Play_Metronome_s" ObjectPath="\Events\Default Work Unit\Play_Metronome_s" DurationType="Infinite">
					<IncludedMemoryFiles>
						<File Id="660299775" Language="SFX">
							<ShortName>Metronome_New.wav</ShortName>
							<Path>SFX\Metronome_New_D79FB2B7.wem</Path>
						</File>
					</IncludedMemoryFiles>
				</Event>
				<Event Id="226855043" Name="Play_Reinforced_Gate" ObjectPath="\Events\Default Work Unit\Play_Reinforced_Gate" DurationType="OneShot" DurationMin="5.557167" DurationMax="5.557167">
					<IncludedMemoryFiles>
						<File Id="988406303" Language="SFX">
							<ShortName>Reinforced_Gate_1.wav</ShortName>
							<Path>SFX\Reinforced_Gate_1_10C4C929.wem</Path>
						</File>
					</IncludedMemoryFiles>
				</Event>
				<Event Id="1807275314" Name="Play_Take_Back_Our_Home" ObjectPath="\Events\Default Work Unit\Play_Take_Back_Our_Home" DurationType="OneShot" DurationMin="3.017333" DurationMax="3.017333">
					<IncludedMemoryFiles>
						<File Id="556155814" Language="SFX">
							<ShortName>Take_Back_Our_Home_2.wav</ShortName>
							<Path>SFX\Take_Back_Our_Home_2_10C4C929.wem</Path>
						</File>
					</IncludedMemoryFiles>
				</Event>
				<Event Id="3448951123" Name="Play_That_One_There" ObjectPath="\Events\Default Work Unit\Play_That_One_There" DurationType="OneShot" DurationMin="6.789021" DurationMax="6.789021">
					<IncludedMemoryFiles>
						<File Id="468849986" Language="SFX">
							<ShortName>That_One_There_2.wav</ShortName>
							<Path>SFX\That_One_There_2_10C4C929.wem</Path>
						</File>
					</IncludedMemoryFiles>
				</Event>
				<Event Id="1170258016" Name="Play_The_Village_is_Ours_Again" ObjectPath="\Events\Default Work Unit\Play_The_Village_is_Ours_Again" DurationType="OneShot" DurationMin="9.197354" DurationMax="9.197354">
					<IncludedMemoryFiles>
						<File Id="351928753" Language="SFX">
							<ShortName>The_Village_is_Ours_Again_1.wav</ShortName>
							<Path>SFX\The_Village_is_Ours_Again_1_10C4C929.wem</Path>
						</File>
					</IncludedMemoryFiles>
				</Event>
				<Event Id="2831686769" Name="Play_Theyre_Retreating" ObjectPath="\Events\Default Work Unit\Play_Theyre_Retreating" DurationType="OneShot" DurationMin="7.162708" DurationMax="7.162708">
					<IncludedMemoryFiles>
						<File Id="67889240" Language="SFX">
							<ShortName>Theyre_Retreating_3.wav</ShortName>
							<Path>SFX\Theyre_Retreating_3_10C4C929.wem</Path>
						</File>
					</IncludedMemoryFiles>
				</Event>
				<Event Id="3559424791" Name="Play_Trap" ObjectPath="\Events\Default Work Unit\Play_Trap" DurationType="OneShot" DurationMin="7.55025" DurationMax="7.55025">
					<IncludedMemoryFiles>
						<File Id="1045215813" Language="SFX">
							<ShortName>Trap_1.wav</ShortName>
							<Path>SFX\Trap_1_10C4C929.wem</Path>
						</File>
					</IncludedMemoryFiles>
				</Event>
				<Event Id="1123782303" Name="Play_We_Need_More_Muscle" ObjectPath="\Events\Default Work Unit\Play_We_Need_More_Muscle" DurationType="OneShot" DurationMin="2.802813" DurationMax="2.802813">
					<IncludedMemoryFiles>
						<File Id="608074595" Language="SFX">
							<ShortName>We_Need_More_Muscle_3.wav</ShortName>
							<Path>SFX\We_Need_More_Muscle_3_10C4C929.wem</Path>
						</File>
					</IncludedMemoryFiles>
				</Event>
			</IncludedEvents>
			<IncludedMemoryFiles>
				<File Id="67889240" Language="SFX">
					<ShortName>Theyre_Retreating_3.wav</ShortName>
					<Path>SFX\Theyre_Retreating_3_10C4C929.wem</Path>
				</File>
				<File Id="90544307" Language="SFX">
					<ShortName>Attack_T2_3.wav</ShortName>
					<Path>SFX\Attack_T2_3_D79FB2B7.wem</Path>
				</File>
				<File Id="106126622" Language="SFX">
					<ShortName>Healing_T2_1.wav</ShortName>
					<Path>SFX\Healing_T2_1_D79FB2B7.wem</Path>
				</File>
				<File Id="141807743" Language="SFX">
					<ShortName>Healing_T2_2.wav</ShortName>
					<Path>SFX\Healing_T2_2_D79FB2B7.wem</Path>
				</File>
				<File Id="153062155" Language="SFX">
					<ShortName>Attack_T2_1.wav</ShortName>
					<Path>SFX\Attack_T2_1_D79FB2B7.wem</Path>
				</File>
				<File Id="163595620" Language="SFX">
					<ShortName>Speed_T1_1.wav</ShortName>
					<Path>SFX\Speed_T1_1_D79FB2B7.wem</Path>
				</File>
				<File Id="185803366" Language="SFX">
					<ShortName>Healing_T1_1.wav</ShortName>
					<Path>SFX\Healing_T1_1_D79FB2B7.wem</Path>
				</File>
				<File Id="190032006" Language="SFX">
					<ShortName>A_Troll_1.wav</ShortName>
					<Path>SFX\A_Troll_1_10C4C929.wem</Path>
				</File>
				<File Id="211984583" Language="SFX">
					<ShortName>Attack_T3_2.wav</ShortName>
					<Path>SFX\Attack_T3_2_D79FB2B7.wem</Path>
				</File>
				<File Id="216635119" Language="SFX">
					<ShortName>Attack_T2_2.wav</ShortName>
					<Path>SFX\Attack_T2_2_D79FB2B7.wem</Path>
				</File>
				<File Id="242612734" Language="SFX">
					<ShortName>Speed_T2_2.wav</ShortName>
					<Path>SFX\Speed_T2_2_D79FB2B7.wem</Path>
				</File>
				<File Id="272182380" Language="SFX">
					<ShortName>Speed_T1_2.wav</ShortName>
					<Path>SFX\Speed_T1_2_D79FB2B7.wem</Path>
				</File>
				<File Id="294660824" Language="SFX">
					<ShortName>Intro_2.wav</ShortName>
					<Path>SFX\Intro_2_10C4C929.wem</Path>
				</File>
				<File Id="307168888" Language="SFX">
					<ShortName>Healing_T2_3.wav</ShortName>
					<Path>SFX\Healing_T2_3_D79FB2B7.wem</Path>
				</File>
				<File Id="322211726" Language="SFX">
					<ShortName>Drum 2.wav</ShortName>
					<Path>SFX\Drum 2_10C4C929.wem</Path>
				</File>
				<File Id="336345604" Language="SFX">
					<ShortName>Healing_T3_3.wav</ShortName>
					<Path>SFX\Healing_T3_3_D79FB2B7.wem</Path>
				</File>
				<File Id="351337165" Language="SFX">
					<ShortName>Healing_T3_1.wav</ShortName>
					<Path>SFX\Healing_T3_1_D79FB2B7.wem</Path>
				</File>
				<File Id="351928753" Language="SFX">
					<ShortName>The_Village_is_Ours_Again_1.wav</ShortName>
					<Path>SFX\The_Village_is_Ours_Again_1_10C4C929.wem</Path>
				</File>
				<File Id="390141292" Language="SFX">
					<ShortName>Drum 4.wav</ShortName>
					<Path>SFX\Drum 4_10C4C929.wem</Path>
				</File>
				<File Id="408029112" Language="SFX">
					<ShortName>Healing_T3_2.wav</ShortName>
					<Path>SFX\Healing_T3_2_D79FB2B7.wem</Path>
				</File>
				<File Id="459815666" Language="SFX">
					<ShortName>Speed_T1_3.wav</ShortName>
					<Path>SFX\Speed_T1_3_D79FB2B7.wem</Path>
				</File>
				<File Id="468849986" Language="SFX">
					<ShortName>That_One_There_2.wav</ShortName>
					<Path>SFX\That_One_There_2_10C4C929.wem</Path>
				</File>
				<File Id="475942752" Language="SFX">
					<ShortName>Speed_T3_1.wav</ShortName>
					<Path>SFX\Speed_T3_1_D79FB2B7.wem</Path>
				</File>
				<File Id="556155814" Language="SFX">
					<ShortName>Take_Back_Our_Home_2.wav</ShortName>
					<Path>SFX\Take_Back_Our_Home_2_10C4C929.wem</Path>
				</File>
				<File Id="587467227" Language="SFX">
					<ShortName>Attack_T1_1.wav</ShortName>
					<Path>SFX\Attack_T1_1_D79FB2B7.wem</Path>
				</File>
				<File Id="608074595" Language="SFX">
					<ShortName>We_Need_More_Muscle_3.wav</ShortName>
					<Path>SFX\We_Need_More_Muscle_3_10C4C929.wem</Path>
				</File>
				<File Id="620322888" Language="SFX">
					<ShortName>Speed_T2_3.wav</ShortName>
					<Path>SFX\Speed_T2_3_D79FB2B7.wem</Path>
				</File>
				<File Id="631214722" Language="SFX">
					<ShortName>Metronome.wav</ShortName>
					<Path>SFX\Metronome_10C4C929.wem</Path>
				</File>
				<File Id="654632406" Language="SFX">
					<ShortName>Attack_T1_3.wav</ShortName>
					<Path>SFX\Attack_T1_3_D79FB2B7.wem</Path>
				</File>
				<File Id="660299775" Language="SFX">
					<ShortName>Metronome_New.wav</ShortName>
					<Path>SFX\Metronome_New_D79FB2B7.wem</Path>
				</File>
				<File Id="710055089" Language="SFX">
					<ShortName>Speed_T2_1.wav</ShortName>
					<Path>SFX\Speed_T2_1_D79FB2B7.wem</Path>
				</File>
				<File Id="729255060" Language="SFX">
					<ShortName>Speed_T3_3.wav</ShortName>
					<Path>SFX\Speed_T3_3_D79FB2B7.wem</Path>
				</File>
				<File Id="731989350" Language="SFX">
					<ShortName>Healing_T1_3.wav</ShortName>
					<Path>SFX\Healing_T1_3_D79FB2B7.wem</Path>
				</File>
				<File Id="758886743" Language="SFX">
					<ShortName>Drum 1.wav</ShortName>
					<Path>SFX\Drum 1_10C4C929.wem</Path>
				</File>
				<File Id="784377917" Language="SFX">
					<ShortName>Attack_T3_3.wav</ShortName>
					<Path>SFX\Attack_T3_3_D79FB2B7.wem</Path>
				</File>
				<File Id="904612785" Language="SFX">
					<ShortName>bg_music.wav</ShortName>
					<Path>SFX\bg_music_D79FB2B7.wem</Path>
				</File>
				<File Id="931607762" Language="SFX">
					<ShortName>Attack_T1_2.wav</ShortName>
					<Path>SFX\Attack_T1_2_D79FB2B7.wem</Path>
				</File>
				<File Id="988406303" Language="SFX">
					<ShortName>Reinforced_Gate_1.wav</ShortName>
					<Path>SFX\Reinforced_Gate_1_10C4C929.wem</Path>
				</File>
				<File Id="1000564919" Language="SFX">
					<ShortName>Drum 3.wav</ShortName>
					<Path>SFX\Drum 3_10C4C929.wem</Path>
				</File>
				<File Id="1020229655" Language="SFX">
					<ShortName>Speed_T3_2.wav</ShortName>
					<Path>SFX\Speed_T3_2_D79FB2B7.wem</Path>
				</File>
				<File Id="1028794606" Language="SFX">
					<ShortName>Attack_T3_1.wav</ShortName>
					<Path>SFX\Attack_T3_1_D79FB2B7.wem</Path>
				</File>
				<File Id="1045215813" Language="SFX">
					<ShortName>Trap_1.wav</ShortName>
					<Path>SFX\Trap_1_10C4C929.wem</Path>
				</File>
				<File Id="1063858419" Language="SFX">
					<ShortName>Healing_T1_2.wav</ShortName>
					<Path>SFX\Healing_T1_2_D79FB2B7.wem</Path>
				</File>
			</IncludedMemoryFiles>
			<GameParameters>
				<GameParameter Id="988953028" Name="SFXVolume" ObjectPath="\Game Parameters\Default Work Unit\Volume\SFXVolume"/>
				<GameParameter Id="2346531308" Name="MusicVolume" ObjectPath="\Game Parameters\Default Work Unit\Volume\MusicVolume"/>
				<GameParameter Id="2591469393" Name="MetronomeVolume" ObjectPath="\Game Parameters\Default Work Unit\Volume\MetronomeVolume"/>
				<GameParameter Id="2918011349" Name="MasterVolume" ObjectPath="\Game Parameters\Default Work Unit\Volume\MasterVolume"/>
				<GameParameter Id="3325181466" Name="VOVolume" ObjectPath="\Game Parameters\Default Work Unit\Volume\VOVolume"/>
			</GameParameters>
			<StateGroups>
				<StateGroup Id="1382114895" Name="Combo_Tiers" ObjectPath="\States\Default Work Unit\Music_120_bpm\Combo_Tiers" GUID="{A5F9CAD7-F127-4815-B1A8-770BDFCD14BF}">
					<States>
						<State Id="748895195" Name="None" ObjectPath="\States\Default Work Unit\Music_120_bpm\Combo_Tiers\None" GUID="{D1152289-093E-4E6E-9EDE-D006011B5D18}"/>
						<State Id="1955617833" Name="T1_Attacking" ObjectPath="\States\Default Work Unit\Music_120_bpm\Combo_Tiers\T1_Attacking" GUID="{5F20EC0D-AAA5-4CF4-91E7-9B4E4F92B40F}"/>
						<State Id="1810093783" Name="T1_Healing" ObjectPath="\States\Default Work Unit\Music_120_bpm\Combo_Tiers\T1_Healing" GUID="{CD64C491-2F3A-4CA5-B7A8-EAD578BDE4DD}"/>
						<State Id="593320872" Name="T1_Speed" ObjectPath="\States\Default Work Unit\Music_120_bpm\Combo_Tiers\T1_Speed" GUID="{343A886D-F1FF-4890-8F4A-005D4F62AB06}"/>
						<State Id="25533574" Name="T2_Attacking" ObjectPath="\States\Default Work Unit\Music_120_bpm\Combo_Tiers\T2_Attacking" GUID="{4C56F35B-E8B1-4EBE-92DC-68A45E93C1A8}"/>
						<State Id="2625074412" Name="T2_Healing" ObjectPath="\States\Default Work Unit\Music_120_bpm\Combo_Tiers\T2_Healing" GUID="{DC578820-B7C8-4441-914C-34F9C419D1B3}"/>
						<State Id="393886535" Name="T2_Speed" ObjectPath="\States\Default Work Unit\Music_120_bpm\Combo_Tiers\T2_Speed" GUID="{14B566F9-61CE-480B-B4E2-16A2DA945C22}"/>
						<State Id="2450158487" Name="T3_Attacking" ObjectPath="\States\Default Work Unit\Music_120_bpm\Combo_Tiers\T3_Attacking" GUID="{5D8C8D93-8CE3-48DC-8CF1-2555AC325FAB}"/>
						<State Id="758121517" Name="T3_Healing" ObjectPath="\States\Default Work Unit\Music_120_bpm\Combo_Tiers\T3_Healing" GUID="{227E5162-1662-4732-88B2-F93AF2AE298A}"/>
						<State Id="1160062082" Name="T3_Speed" ObjectPath="\States\Default Work Unit\Music_120_bpm\Combo_Tiers\T3_Speed" GUID="{063107F4-D107-4DEE-9841-86FC95AF9026}"/>
					</States>
				</StateGroup>
			</StateGroups>
		</SoundBank>
	</SoundBanks>
</SoundBanksInfo>
